{
  "id": "biodex",
  "name": "Biodex",
  "categoryId": "manufacturing",
  "description": "Multi-tiered intermediate concept",
  "investment_24m": "533",
  "hostedtype": "OnPremise",
  "licensing_cost": "40",
  "status_color": "#00FF00",
  "type": "OffShelf",
  "support_cost": "212",
  "deployment_date": "16/12/12",
  "end_of_maintenance": "18/6/17",
  "department": "Support",
  "status": "Active",
  "end_of_life": "17/6/18",
  "months_to_renew_support": "30",
  "sme_email": "Liam.Estick@memento.net.au",
  "investment_number": "281"
}